__init__.py
bigbucks_db.py
bigbucks_db-0.0.6.dist-info/LICENSE
bigbucks_db-0.0.6.dist-info/METADATA
bigbucks_db-0.0.6.dist-info/WHEEL
bigbucks_db-0.0.6.dist-info/top_level.txt
bigbucks_db-0.0.6.dist-info/RECORD
